fhirmodels/__init__.py
fhirmodels/cli.py
fhirmodels/constants.py
fhirmodels/fhir_base_model.py
fhirmodels/fhir_package.py
fhirmodels/generator.py
fhirmodels/model_init.j2
fhirmodels/structure_definition_model.j2
fhirmodels/test_R4_condition.py
fhirmodels/utils.py
fhirmodels/R4/Account.py
fhirmodels/R4/ActivityDefinition.py
fhirmodels/R4/Address.py
fhirmodels/R4/AdverseEvent.py
fhirmodels/R4/Age.py
fhirmodels/R4/AllergyIntolerance.py
fhirmodels/R4/Annotation.py
fhirmodels/R4/Appointment.py
fhirmodels/R4/AppointmentResponse.py
fhirmodels/R4/Attachment.py
fhirmodels/R4/AuditEvent.py
fhirmodels/R4/BackboneElement.py
fhirmodels/R4/Basic.py
fhirmodels/R4/Binary.py
fhirmodels/R4/BiologicallyDerivedProduct.py
fhirmodels/R4/BodyStructure.py
fhirmodels/R4/Bundle.py
fhirmodels/R4/CapabilityStatement.py
fhirmodels/R4/CarePlan.py
fhirmodels/R4/CareTeam.py
fhirmodels/R4/CatalogEntry.py
fhirmodels/R4/ChargeItem.py
fhirmodels/R4/ChargeItemDefinition.py
fhirmodels/R4/Claim.py
fhirmodels/R4/ClaimResponse.py
fhirmodels/R4/ClinicalImpression.py
fhirmodels/R4/CodeSystem.py
fhirmodels/R4/CodeableConcept.py
fhirmodels/R4/Coding.py
fhirmodels/R4/Communication.py
fhirmodels/R4/CommunicationRequest.py
fhirmodels/R4/CompartmentDefinition.py
fhirmodels/R4/Composition.py
fhirmodels/R4/ConceptMap.py
fhirmodels/R4/Condition.py
fhirmodels/R4/Consent.py
fhirmodels/R4/ContactDetail.py
fhirmodels/R4/ContactPoint.py
fhirmodels/R4/Contract.py
fhirmodels/R4/Contributor.py
fhirmodels/R4/Count.py
fhirmodels/R4/Coverage.py
fhirmodels/R4/CoverageEligibilityRequest.py
fhirmodels/R4/CoverageEligibilityResponse.py
fhirmodels/R4/DataRequirement.py
fhirmodels/R4/Definition.py
fhirmodels/R4/DetectedIssue.py
fhirmodels/R4/Device.py
fhirmodels/R4/DeviceDefinition.py
fhirmodels/R4/DeviceMetric.py
fhirmodels/R4/DeviceRequest.py
fhirmodels/R4/DeviceUseStatement.py
fhirmodels/R4/DiagnosticReport.py
fhirmodels/R4/Distance.py
fhirmodels/R4/DocumentManifest.py
fhirmodels/R4/DocumentReference.py
fhirmodels-0.1.3.dist-info/METADATA
fhirmodels-0.1.3.dist-info/WHEEL
fhirmodels-0.1.3.dist-info/entry_points.txt
fhirmodels-0.1.3.dist-info/licenses/LICENSE
fhirmodels-0.1.3.dist-info/RECORD
